chemformer/bart_vocab.txt
chemformer/bart_vocab_downstream.txt
chemformer/requirements.txt
chemformer/example_scripts/finetune_regression/finetuneRegr.py
chemformer/example_scripts/finetune_regression/finetune_regression_modules.py
chemformer/example_scripts/finetune_regression/prop_bart_vocab.txt
chemformer/example_scripts/finetune_regression/trainRegr.py
chemformer/molbart/__init__.py
chemformer/molbart/build_tokeniser.py
chemformer/molbart/decoder.py
chemformer/molbart/evaluate.py
chemformer/molbart/fine_tune.py
chemformer/molbart/predict.py
chemformer/molbart/tokeniser.py
chemformer/molbart/train.py
chemformer/molbart/util.py
chemformer/molbart/data/__init__.py
chemformer/molbart/data/datamodules.py
chemformer/molbart/data/datasets.py
chemformer/molbart/data/util.py
chemformer/molbart/models/__init__.py
chemformer/molbart/models/pre_train.py
chemformer/molbart/models/util.py
chemformer/test/__init__.py
chemformer/test/decoder_test.py
chemformer/test/pre_train_model_test.py
chemformer/test/tokeniser_test.py
syntheseus_chemformer-0.3.0.dist-info/licenses/AUTHORS.md
syntheseus_chemformer-0.3.0.dist-info/licenses/LICENSE
syntheseus_chemformer-0.3.0.dist-info/METADATA
syntheseus_chemformer-0.3.0.dist-info/WHEEL
syntheseus_chemformer-0.3.0.dist-info/top_level.txt
syntheseus_chemformer-0.3.0.dist-info/RECORD
