Metadata-Version: 2.4
Name: syntheseus-chemformer
Version: 0.3.0
Summary: Fork of Chemformer for use in the syntheseus library
Home-page: https://github.com/kmaziarz/Chemformer
License-File: LICENSE
License-File: AUTHORS.md
Requires-Dist: syntheseus-PySMILESutils
Dynamic: home-page
Dynamic: license-file
Dynamic: requires-dist
Dynamic: summary
